fseval/__init__.py
fseval/main.py
fseval/types.py
fseval/adapters/__init__.py
fseval/adapters/openml.py
fseval/adapters/wandb.py
fseval/callbacks/__init__.py
fseval/callbacks/_base_export_callback.py
fseval/callbacks/to_csv.py
fseval/callbacks/to_sql.py
fseval/callbacks/to_wandb.py
fseval/conf/__init__.py
fseval/conf/callbacks/to_csv.yaml
fseval/conf/callbacks/to_sql.yaml
fseval/conf/callbacks/to_wandb.yaml
fseval/conf/cv/kfold.yaml
fseval/conf/cv/train_test_split.yaml
fseval/conf/hydra/help/default.yaml
fseval/conf/hydra/job/default.yaml
fseval/conf/metrics/feature_importances.yaml
fseval/conf/metrics/ranking_scores.yaml
fseval/conf/metrics/validation_scores.yaml
fseval/conf/resample/bootstrap.yaml
fseval/conf/resample/shuffle.yaml
fseval/conf/storage/local.yaml
fseval/conf/storage/mock.yaml
fseval/conf/storage/wandb.yaml
fseval/config/__init__.py
fseval/config/cross_validator.py
fseval/config/dataset.py
fseval/config/estimator.py
fseval/config/pipeline.py
fseval/config/resample.py
fseval/config/storage.py
fseval/config/adapters/__init__.py
fseval/config/adapters/openml_dataset.py
fseval/config/adapters/wandb_dataset.py
fseval/config/callbacks/__init__.py
fseval/config/callbacks/to_csv.py
fseval/config/callbacks/to_sql.py
fseval/config/callbacks/to_wandb.py
fseval/metrics/__init__.py
fseval/metrics/feature_importances.py
fseval/metrics/ranking_scores.py
fseval/metrics/validation_scores.py
fseval/pipeline/__init__.py
fseval/pipeline/cv.py
fseval/pipeline/dataset.py
fseval/pipeline/estimator.py
fseval/pipeline/resample.py
fseval/pipelines/__init__.py
fseval/pipelines/_callback_collection.py
fseval/pipelines/_experiment.py
fseval/pipelines/_pipeline.py
fseval/pipelines/rank_and_validate/__init__.py
fseval/pipelines/rank_and_validate/_config.py
fseval/pipelines/rank_and_validate/_dataset_validator.py
fseval/pipelines/rank_and_validate/_ranking_validator.py
fseval/pipelines/rank_and_validate/_subset_validator.py
fseval/pipelines/rank_and_validate/_support_validator.py
fseval-3.1.0.dist-info/LICENSE
fseval-3.1.0.dist-info/METADATA
fseval-3.1.0.dist-info/WHEEL
fseval-3.1.0.dist-info/entry_points.txt
fseval-3.1.0.dist-info/top_level.txt
fseval-3.1.0.dist-info/RECORD
