Metadata-Version: 2.1
Name: fseval
Version: 3.1.0
Summary: Benchmarking framework for Feature Selection and Feature Ranking algorithms 🚀
Home-page: https://github.com/dunnkers/fseval
Author: Jeroen Overschie
Author-email: jeroen@darius.nl
Maintainer: Jeroen Overschie
Maintainer-email: jeroen@darius.nl
License: MIT
Project-URL: Github, https://github.com/dunnkers/fseval
Project-URL: Bug Tracker, https://github.com/dunnkers/fseval/issues
Project-URL: Documentation, https://dunnkers.com/fseval
Classifier: License :: OSI Approved :: MIT License
Classifier: Development Status :: 4 - Beta
Classifier: Programming Language :: Python :: 3.7
Classifier: Programming Language :: Python :: 3.8
Classifier: Programming Language :: Python :: 3.9
Classifier: Programming Language :: Python :: 3.10
Classifier: Operating System :: POSIX :: Linux
Classifier: Operating System :: MacOS
Classifier: Operating System :: Microsoft :: Windows
Classifier: Typing :: Typed
Classifier: Topic :: Scientific/Engineering
Classifier: Topic :: Scientific/Engineering :: Artificial Intelligence
Classifier: Topic :: Software Development
Classifier: Topic :: Software Development :: Libraries :: Python Modules
Classifier: Topic :: System :: Benchmark
Requires-Python: >= 3.7
License-File: LICENSE
Requires-Dist: hydra-core (>=1.1.2)
Requires-Dist: hydra-colorlog (>=1.1.0)
Requires-Dist: numpy (>=1.19)
Requires-Dist: pandas (>=1.1)
Requires-Dist: scikit-learn (>=0.24)
Requires-Dist: humanfriendly (>=9)
Requires-Dist: shortuuid (>=1.0)
Requires-Dist: overrides (>=6)
Requires-Dist: SQLAlchemy (>=1)
